apimaticcalculator/__init__.py
apimaticcalculator/api_helper.py
apimaticcalculator/apimaticcalculator_client.py
apimaticcalculator/configuration.py
apimaticcalculator/decorators.py
apimaticcalculator/controllers/__init__.py
apimaticcalculator/controllers/base_controller.py
apimaticcalculator/controllers/operation_controller.py
apimaticcalculator/exceptions/__init__.py
apimaticcalculator/exceptions/api_exception.py
apimaticcalculator/http/__init__.py
apimaticcalculator/http/http_call_back.py
apimaticcalculator/http/http_client.py
apimaticcalculator/http/http_method_enum.py
apimaticcalculator/http/http_request.py
apimaticcalculator/http/http_response.py
apimaticcalculator/http/requests_client.py
apimaticcalculator/models/__init__.py
apimaticcalculator/models/operation_enum.py
apimaticcalculator/utilities/__init__.py
apimaticcalculator/utilities/file_wrapper.py
tests/__init__.py
tests/http_response_catcher.py
tests/test_helper.py
tests/controllers/__init__.py
tests/controllers/controller_test_base.py
tests/controllers/test_operation_controller.py
MyPythonCalculator-1.0.dist-info/LICENSE
MyPythonCalculator-1.0.dist-info/METADATA
MyPythonCalculator-1.0.dist-info/WHEEL
MyPythonCalculator-1.0.dist-info/top_level.txt
MyPythonCalculator-1.0.dist-info/RECORD
